lescolors/__init__.py
lescolors/colors.py
lescolors-1.0.2.dist-info/LICENSE
lescolors-1.0.2.dist-info/METADATA
lescolors-1.0.2.dist-info/WHEEL
lescolors-1.0.2.dist-info/top_level.txt
lescolors-1.0.2.dist-info/RECORD
