Metadata-Version: 2.1
Name: lescolors
Version: 1.0.2
Summary: Color Manipulation and Analysis Utilities
Home-page: https://github.com/Anish177/lescolors
Author: Anish Panda
Author-email: anip1776@gmail.com
License: MIT
Classifier: Programming Language :: Python :: 3
Classifier: License :: OSI Approved :: MIT License
Classifier: Operating System :: OS Independent
Requires-Python: >=3.6
License-File: LICENSE
Requires-Dist: requests
Requires-Dist: colorthief
